funpinpin_cli/__init__.py
funpinpin_cli/config.py
funpinpin_cli/core/__init__.py
funpinpin_cli/core/app/__init__.py
funpinpin_cli/core/app/connect.py
funpinpin_cli/core/app/create/__init__.py
funpinpin_cli/core/app/create/node.py
funpinpin_cli/core/app/open.py
funpinpin_cli/core/app/serve.py
funpinpin_cli/core/auth.py
funpinpin_cli/core/env_file.py
funpinpin_cli/core/login.py
funpinpin_cli/core/logout.py
funpinpin_cli/core/populate/__init__.py
funpinpin_cli/core/populate/customer.py
funpinpin_cli/core/populate/haikunator_helper.py
funpinpin_cli/core/populate/order.py
funpinpin_cli/core/populate/product.py
funpinpin_cli/core/project.py
funpinpin_cli/core/store.py
funpinpin_cli/core/switch.py
funpinpin_cli/core/tunnel.py
funpinpin_cli/core/util/__init__.py
funpinpin_cli/core/util/context.py
funpinpin_cli/core/util/exception.py
funpinpin_cli/core/util/simple_db.py
funpinpin_cli/core/util/simple_http_server.py
funpinpin_cli/core/util/simple_supervision.py
funpinpin_cli/core/version.py
funpinpin_cli/core/whoami.py
funpinpin_cli/main.py
funpinpin_cli/scripts/__init__.py
funpinpin_cli/scripts/app/__init__.py
funpinpin_cli/scripts/app/connect.py
funpinpin_cli/scripts/app/create.py
funpinpin_cli/scripts/app/open.py
funpinpin_cli/scripts/app/serve.py
funpinpin_cli/scripts/app/tunnels.py
funpinpin_cli/scripts/app/validator.py
funpinpin_cli/scripts/command.py
funpinpin_cli/scripts/extension/__init__.py
funpinpin_cli/scripts/extension/tunnels.py
funpinpin_cli/scripts/extension/validator.py
funpinpin_cli/scripts/help.py
funpinpin_cli/scripts/login.py
funpinpin_cli/scripts/logout.py
funpinpin_cli/scripts/message.py
funpinpin_cli/scripts/populate/__init__.py
funpinpin_cli/scripts/populate/customer.py
funpinpin_cli/scripts/populate/draftorder.py
funpinpin_cli/scripts/populate/product.py
funpinpin_cli/scripts/populate/validator.py
funpinpin_cli/scripts/store.py
funpinpin_cli/scripts/switch.py
funpinpin_cli/scripts/util.py
funpinpin_cli/scripts/version.py
funpinpin_cli-1.1.6.dist-info/entry_points.txt
funpinpin_cli-1.1.6.dist-info/WHEEL
funpinpin_cli-1.1.6.dist-info/METADATA
funpinpin_cli-1.1.6.dist-info/RECORD
