Metadata-Version: 2.1
Name: funpinpin-cli
Version: 1.1.6
Summary: funpinpin cli tool
Author: funpinpin
Author-email: support@funpinpin.cn
Requires-Python: >=3.7,<4.0
Classifier: Programming Language :: Python :: 3
Classifier: Programming Language :: Python :: 3.10
Classifier: Programming Language :: Python :: 3.7
Classifier: Programming Language :: Python :: 3.8
Classifier: Programming Language :: Python :: 3.9
Requires-Dist: PyYAML (>=6.0,<7.0)
Requires-Dist: asyncio (>=3.4.3,<4.0.0)
Requires-Dist: click (>=8.1.2,<9.0.0)
Requires-Dist: haikunator (>=2.1.0,<3.0.0)
Requires-Dist: pickleDB (>=0.9.2,<0.10.0)
Requires-Dist: psutil (>=5.9.1,<6.0.0)
Requires-Dist: python-graphql-client (>=0.4.3,<0.5.0)
Requires-Dist: questionary (>=1.10.0,<2.0.0)
Requires-Dist: requests (>=2.27.1,<3.0.0)
